Perceptron in Verilog/mem_w.v
module mem_w (
    clk,
    mem_ena,
    wr_rd,
    addr,
    data_in,
    data_out
);

    input clk;
    input mem_ena;
    input wr_rd;
    input [15:0] data_in;
    output reg [15:0] data_out;
    input [5:0] addr;

  reg [15:0] mem[2:0];
  integer file, flag, j;
  real f;

  initial begin
    file = $fopen("w.txt", "r");
    flag = $fscanf(file, "%f", f);
    j = 0;
    while (j <= 2 && flag != 0) begin
      mem[j] = f * 512;
      flag   = $fscanf(file, "%f", f);
      $display("input:%d,j=%d,flag=%d", mem[j], j, flag);
      j = j + 1;
    end
    $fclose(file);
  end

  always @(posedge clk) begin
    if (mem_ena) begin
      if (wr_rd) mem[addr] <= data_in;
      else data_out <= mem[addr];
    end
  end

endmodule

A-Perceptron/mem_x2.v
module mem_x2 (
    clk,
    mem_ena,
    wr_rd,
    addr,
    data_in,
    data_out
);

  input clk;
  input mem_ena;
  input wr_rd;
  input [9:0] addr;
  input [15:0] data_in;
  output reg [15:0] data_out;

  reg [15:0] mem[1023:0];

  integer file, flag, j;
  real f;
  initial begin
    file = $fopen("x2.txt", "r");
    flag = $fscanf(file, "%f", f);
    j = 0;
    while (j <= 1023 && flag != 0) begin
      mem[j] = f * 512;
      $display("input:%d,j=%d,flag=%d", mem[j], j, flag);
      flag = $fscanf(file, "%f", f);
      j = j + 1;
    end
    $fclose(file);
  end

  always @(posedge clk) begin
    if (mem_ena) begin
      if (wr_rd) mem[addr] <= data_in;
      else data_out <= mem[addr];
    end
  end

endmodule

Perceptron in Verilog/mem_x1.v
module mem_x1 (
    clk,
    mem_ena,
    wr_rd,
    addr,
    data_in,
    data_out
);

  input clk;
  input mem_ena;
  input wr_rd;
  input [9:0] addr;
  input [15:0] data_in;
  output reg [15:0] data_out;

  reg [15:0] mem[1023:0];

  integer file, j, flag;
  real f;
  initial begin
    file = $fopen("x1.txt", "r");
    flag = $fscanf(file, "%f", f);
    j = 0;
    while (j <= 1023 && flag != 0) begin
      mem[j] = f * 512;
      flag   = $fscanf(file, "%f", f);
      $display("input:%d,j=%d,flag=%d", mem[j], j, flag);
      j = j + 1;
    end
    $fclose(file);
  end

  always @(posedge clk)

    if (mem_ena)
      if (wr_rd) begin
        mem[addr] <= data_in;
      end else begin
        data_out <= mem[addr];
      end
endmodule

Perceptron in Verilog/mem_label.v
module mem_label (
    clk,
    mem_ena,
    wr_rd,
    addr,
    data_in,
    data_out
);

  input clk;
  input mem_ena;
  input wr_rd;
  input [9:0] addr;
  input [15:0] data_in;
  output reg [15:0] data_out;

  reg [15:0] mem[1023:0];
  integer file, flag, j;
  real f;

  initial begin
    file = $fopen("z.txt", "r");
    flag = $fscanf(file, "%f", f);
    j = 0;
    while (j <= 1023 && flag != 0) begin
      mem[j] = f*512;  
      $display("input:%d,j=%d,flag=%d", mem[j],j,flag);
      flag = $fscanf(file, "%f", f);
      j = j + 1;
    end
    $fclose(file);
  end

  always @(posedge clk) begin
    if (mem_ena) begin
      if (wr_rd) mem[addr] <= data_in;
      else data_out <= mem[addr];
    end
  end
endmodule

A-Perceptron/core_perceptron.v
module core_perceptron (
    clk,
    rst,
    control,
    x1_in,
    x2_in,
    label_in,
    x1_cnt,
    x2_cnt,
    label_cnt,
    // x1_out,
    // x2_out,
    // label_out,
    x1_en,
    x2_en,
    label_en,
    x1_w,
    x2_w,
    label_w,
    w_en,
    w_w,
    w_in,
    w_out,
    w_cnt
);

  input clk;
  input rst;
  input [3:0] control;

  input [15:0] x1_in, x2_in, label_in;
  input [9:0] x1_cnt, x2_cnt, label_cnt;
  // output reg[15:0] x1_out , x2_out , label_out;
  output reg x1_en, x2_en, label_en;
  output reg x1_w, x2_w, label_w;

  input [15:0] w_in;
  output  [15:0] w_out;
  output reg [5:0] w_cnt;
  output reg w_en;
  output reg w_w;

  reg end_of_cal;
  reg end_of_up;
  reg end_of_rd;

  reg signed [15:0] my_x1, my_x2, my_label;
  reg signed [15:0] my_w1, my_w2, my_bias;
  reg [15:0] w1_out, w2_out, bias_out, w_out;
  reg signed [31:0] sum;
  reg signed [31:0] mult;
  reg signed [15:0] differ;
  reg F;

  reg [5:0] state;
  reg [5:0] read_state;
  reg [8:0] calculate_state;
  reg [6:0] update_state;

  parameter start     =5'b00001,
            read      =5'b00010,
            calculate =5'b00100,
            update    = 5'b01000,
            finish    = 5'b10000,

            read_init   = 5'b00001,
            read_p1     = 5'b00010,
            read_p2     = 5'b00100,
            read_bias   = 5'b01000,
            read_end    = 5'b10000,
         
            cal_init  = 8'b00000001,
            cal_part1 = 8'b00000010,
            cal_part2 = 8'b00000100,
            cal_sum   = 8'b00001000,
            cal_bias  = 8'b00010000,
            cal_F     = 8'b00100000,
            cal_differ= 8'b01000000,
            cal_end   = 8'b10000000,
            
            upd_init  = 6'b000001,
            upd_bias  = 6'b000010,
            upd_part2 = 6'b000100,
            upd_part1 = 6'b001000,
            upd_wr    = 6'b010000,
            upd_end   = 6'b100000;

  always @(posedge clk) begin
    if (rst) begin
      state           <= start;
      read_state     <= 6'bxxxxxx;
      calculate_state<= 9'bxxxxxxxxx;
      update_state   <= 7'bxxxxxxx;

      end_of_rd       <= 0;
      end_of_cal      <= 0;
      end_of_up       <= 0;
      w_cnt           <= 0;
      x1_en           <= 1;
      x2_en           <= 1;
      label_en        <= 1;
      w_en            <= 1;
      x1_w            <= 0;
      x2_w            <= 0;
      label_w         <= 0;
      w_w             <= 0;
      my_x1           <= x1_in;
      my_x2           <= x2_in;
      my_label        <= label_in / 512;

    end else begin
      case (state)
        start: begin
          if (control[0] == 1) begin
            state <= read;
          end else begin
            state <= start;
          end
        end

        read: begin
          if (control[1] == 1 && end_of_rd) begin
            state <= calculate;
          end else begin
            state <= read;
            read_state <= read_init;
            case (read_state)
              read_init: begin
                end_of_rd <= 0;
                read_state <= read_p1;
                w_cnt <= w_cnt + 1;
              end
              read_p1: begin
                read_state <= read_p2;
                my_w1 <= w_in;
                w_cnt <= w_cnt + 1;
              end
              read_p2: begin
                my_w2 <= w_in;
                // w_cnt <= w_cnt + 1;
                read_state <= read_bias;
              end
              read_bias: begin
                my_bias <= w_in;
                read_state <= read_end;
              end
              read_end: begin
                end_of_rd  <= 1;
                read_state <= read_init;
              end
              default: begin
                read_state <= read_init;
              end
            endcase
          end
        end

        calculate: begin
          if (control[2] == 1 && end_of_cal) begin
            state <= update;
          end else begin
            state <= calculate;
            calculate_state <= cal_init;
            case (calculate_state)
              cal_init: begin
                sum <= 32'b0;
                differ <= 32'b0;
                mult <= 32'b0;
                end_of_cal <= 0;
                calculate_state <= cal_part1;
              end
              cal_part1: begin
                mult <= my_w1 * my_x1;
                calculate_state <= cal_part2;
              end
              cal_part2: begin
                sum <= sum + mult;
                mult <= my_w2 * my_x2;
                calculate_state <= cal_sum;
              end
              cal_sum: begin
                sum <= sum + mult;
                calculate_state <= cal_bias;
              end
              cal_bias: begin
                sum <= sum + my_bias;
                calculate_state <= cal_F;
              end
              cal_F: begin
                F <= (sum >= 0) ? 1 : 0;
                calculate_state <= cal_differ;
              end
              cal_differ: begin
                differ <= my_label - F;
                calculate_state <= cal_end;
              end
              cal_end: begin
                calculate_state <= cal_init;
                end_of_cal <= 1;
              end
              default: begin
                calculate_state <= cal_init;
              end
            endcase
          end
        end
        
        update: begin
          if (control[3] == 1 && end_of_up) begin
            state <= finish;
          end else begin
            state <= update;
            update_state <= upd_init;
            case (update_state)
              upd_init: begin
                end_of_up <= 0;
                update_state <= upd_bias;
                w_w <= 1;
              end
              upd_bias: begin
                bias_out <= my_bias + differ * 512;
                update_state <= upd_part2;
              end
              upd_part2: begin
                w2_out <= my_w2 + differ * my_x2;
                w_out <= bias_out;
                update_state <= upd_part1;
              end
              upd_part1: begin
                w1_out <= my_w1 + differ * my_x1;
                w_cnt <= w_cnt - 1;
                w_out <= w2_out;
                update_state <= upd_wr;
              end
              upd_wr: begin
                w_cnt <= w_cnt - 1;
                w_out <= w1_out;
                update_state <= upd_end;
              end
              upd_end: begin
                end_of_up <= 1;
                w_w <= 0;
                update_state <= upd_init;
              end
              default: begin
                update_state <= upd_init;
              end
            endcase
          end
        end

        finish: begin
          // my_w1 <= w1_out;
          // my_w2 <= w2_out;
          // my_bias <= bias_out;
          state <= start;
        end
        default: begin
          state <= start;
        end
      endcase
    end
  end
endmodule

A-Perceptron/core_perceptron_top.v
module core_perceptron_top();

  reg clk;
  reg rst;
  reg [3:0] control;
  wire x1_w,x2_w,label_w,w_w;
  wire x1_en,  x2_en, label_en, w_en;
  wire[15:0] x1_in, x2_in, label_in, w_in, w_out;
  reg[9:0] x1_cnt, x2_cnt, label_cnt;
  wire[5:0] w_cnt;
  reg[15:0] x1_out, x2_out, label_out;

  core_perceptron core(
    clk,
    rst,
    control,
    x1_in,
    x2_in,
    label_in,
    x1_cnt,
    x2_cnt,
    label_cnt,
    // x1_out,
    // x2_out,
    // label_out,
    x1_en,
    x2_en,
    label_en,
    x1_w,
    x2_w,
    label_w,
    w_en,
    w_w,
    w_in,
    w_out,
    w_cnt
    );

mem_label label(clk,label_en,label_w,label_cnt,label_out, label_in);

mem_x1 x1(clk,x1_en, x1_w, x1_cnt, x1_out, x1_in);

mem_x2 x2(clk,x2_en, x2_w, x2_cnt, x2_out, x2_in);

mem_w w(clk,w_en, w_w, w_cnt, w_out, w_in);


  always
    begin
      clk=1; #5; clk=0; #5;
    end

initial 
    begin
      rst            <= 0;
      control        <= 0;
      #10;
      rst            <= 1;
      x1_cnt    <= 0;
      x2_cnt    <= 0;
      label_cnt <= 0;
      #50;
      rst            <= 0;
      control        <= 4'b1111;
      #300;
      repeat(500) begin
      rst            <= 0;
      control        <= 0;
      #10;
      rst            <= 1;
      x1_cnt    <= x1_cnt+1;
      x2_cnt    <= x2_cnt+1;
      label_cnt <= label_cnt+1;
      #50;
      rst            <= 0;
      control        <= 4'b1111;
      #800;
      end
      $finish;
    end

  initial 
    begin
      $dumpfile("perceptron.vcd");
      $dumpvars(0,core_perceptron_top);
    end

endmodule

Perceptron in Verilog/perceptron.vcd
$date
	Thu Jul 10 15:16:18 2025
$end
$version
	Icarus Verilog
$end
$timescale
	1s
$end
$scope module core_perceptron_top $end
$var wire 1 ! x2_w $end
$var wire 16 " x2_in [15:0] $end
$var wire 1 # x2_en $end
$var wire 1 $ x1_w $end
$var wire 16 % x1_in [15:0] $end
$var wire 1 & x1_en $end
$var wire 1 ' w_w $end
$var wire 16 ( w_out [15:0] $end
$var wire 16 ) w_in [15:0] $end
$var wire 1 * w_en $end
$var wire 6 + w_cnt [5:0] $end
$var wire 1 , label_w $end
$var wire 16 - label_in [15:0] $end
$var wire 1 . label_en $end
$var reg 1 / clk $end
$var reg 4 0 control [3:0] $end
$var reg 10 1 label_cnt [9:0] $end
$var reg 16 2 label_out [15:0] $end
$var reg 1 3 rst $end
$var reg 10 4 x1_cnt [9:0] $end
$var reg 16 5 x1_out [15:0] $end
$var reg 10 6 x2_cnt [9:0] $end
$var reg 16 7 x2_out [15:0] $end
$scope module core $end
$var wire 1 / clk $end
$var wire 4 8 control [3:0] $end
$var wire 10 9 label_cnt [9:0] $end
$var wire 1 3 rst $end
$var wire 10 : x1_cnt [9:0] $end
$var wire 10 ; x2_cnt [9:0] $end
$var wire 16 < x2_in [15:0] $end
$var wire 16 = x1_in [15:0] $end
$var wire 16 > w_in [15:0] $end
$var wire 16 ? label_in [15:0] $end
$var parameter 8 @ cal_F $end
$var parameter 8 A cal_bias $end
$var parameter 8 B cal_differ $end
$var parameter 8 C cal_end $end
$var parameter 8 D cal_init $end
$var parameter 8 E cal_part1 $end
$var parameter 8 F cal_part2 $end
$var parameter 8 G cal_sum $end
$var parameter 5 H calculate $end
$var parameter 5 I finish $end
$var parameter 5 J read $end
$var parameter 5 K read_bias $end
$var parameter 5 L read_end $end
$var parameter 5 M read_init $end
$var parameter 5 N read_p1 $end
$var parameter 5 O read_p2 $end
$var parameter 5 P start $end
$var parameter 6 Q upd_bias $end
$var parameter 6 R upd_end $end
$var parameter 6 S upd_init $end
$var parameter 6 T upd_part1 $end
$var parameter 6 U upd_part2 $end
$var parameter 6 V upd_wr $end
$var parameter 5 W update $end
$var reg 1 X F $end
$var reg 16 Y bias_out [15:0] $end
$var reg 9 Z calculate_state [8:0] $end
$var reg 16 [ differ [15:0] $end
$var reg 1 \ end_of_cal $end
$var reg 1 ] end_of_rd $end
$var reg 1 ^ end_of_up $end
$var reg 1 . label_en $end
$var reg 1 , label_w $end
$var reg 32 _ mult [31:0] $end
$var reg 16 ` my_bias [15:0] $end
$var reg 16 a my_label [15:0] $end
$var reg 16 b my_w1 [15:0] $end
$var reg 16 c my_w2 [15:0] $end
$var reg 16 d my_x1 [15:0] $end
$var reg 16 e my_x2 [15:0] $end
$var reg 6 f read_state [5:0] $end
$var reg 6 g state [5:0] $end
$var reg 32 h sum [31:0] $end
$var reg 7 i update_state [6:0] $end
$var reg 16 j w1_out [15:0] $end
$var reg 16 k w2_out [15:0] $end
$var reg 6 l w_cnt [5:0] $end
$var reg 1 * w_en $end
$var reg 16 m w_out [15:0] $end
$var reg 1 ' w_w $end
$var reg 1 & x1_en $end
$var reg 1 $ x1_w $end
$var reg 1 # x2_en $end
$var reg 1 ! x2_w $end
$upscope $end
$scope module label $end
$var wire 10 n addr [9:0] $end
$var wire 1 / clk $end
$var wire 16 o data_in [15:0] $end
$var wire 1 . mem_ena $end
$var wire 1 , wr_rd $end
$var reg 16 p data_out [15:0] $end
$var real 1 q f $end
$var integer 32 r file [31:0] $end
$var integer 32 s flag [31:0] $end
$var integer 32 t j [31:0] $end
$upscope $end
$scope module w $end
$var wire 6 u addr [5:0] $end
$var wire 1 / clk $end
$var wire 16 v data_in [15:0] $end
$var wire 1 * mem_ena $end
$var wire 1 ' wr_rd $end
$var reg 16 w data_out [15:0] $end
$var real 1 x f $end
$var integer 32 y file [31:0] $end
$var integer 32 z flag [31:0] $end
$var integer 32 { j [31:0] $end
$upscope $end
$scope module x1 $end
$var wire 10 | addr [9:0] $end
$var wire 1 / clk $end
$var wire 16 } data_in [15:0] $end
$var wire 1 & mem_ena $end
$var wire 1 $ wr_rd $end
$var reg 16 ~ data_out [15:0] $end
$var real 1 !" f $end
$var integer 32 "" file [31:0] $end
$var integer 32 #" flag [31:0] $end
$var integer 32 $" j [31:0] $end
$upscope $end
$scope module x2 $end
$var wire 10 %" addr [9:0] $end
$var wire 1 / clk $end
$var wire 16 &" data_in [15:0] $end
$var wire 1 # mem_ena $end
$var wire 1 ! wr_rd $end
$var reg 16 '" data_out [15:0] $end
$var real 1 (" f $end
$var integer 32 )" file [31:0] $end
$var integer 32 *" flag [31:0] $end
$var integer 32 +" j [31:0] $end
$upscope $end
$upscope $end
$enddefinitions $end
$comment Show the parameter values. $end
$dumpall
b1000 W
b10000 V
b100 U
b1000 T
b1 S
b100000 R
b10 Q
b1 P
b100 O
b10 N
b1 M
b10000 L
b1000 K
b10 J
b10000 I
b100 H
b1000 G
b100 F
b10 E
b1 D
b10000000 C
b1000000 B
b10000 A
b100000 @
$end
#0
$dumpvars
b10000000000 +"
b11111111111111111111111111111111 *"
b10000000000000000000000000000011 )"
r-0.17 ("
bx '"
bx &"
bx %"
b10000000000 $"
b11111111111111111111111111111111 #"
b10000000000000000000000000000011 ""
r0.24 !"
bx ~
bx }
bx |
b11 {
b11111111111111111111111111111111 z
b10000000000000000000000000000011 y
r0.5 x
bx w
bx v
bx u
b10000000000 t
b11111111111111111111111111111111 s
b10000000000000000000000000000011 r
r1 q
bx p
bx o
bx n
bx m
bx l
bx k
bx j
bx i
bx h
b1 g
bx f
bx e
bx d
bx c
bx b
bx a
bx `
bx _
x^
x]
x\
bx [
bx Z
bx Y
xX
bx ?
bx >
bx =
bx <
bx ;
bx :
bx 9
b0 8
bx 7
bx 6
bx 5
bx 4
03
bx 2
bx 1
b0 0
1/
x.
bx -
x,
bx +
x*
bx )
bx (
x'
x&
bx %
x$
x#
bx "
x!
$end
#5
0/
#10
b0 1
b0 9
b0 n
b0 6
b0 ;
b0 %"
b0 4
b0 :
b0 |
13
1/
#15
0/
#20
0'
0,
0!
0$
1*
1.
1#
1&
b0 +
b0 l
b0 u
0^
0\
0]
1/
#25
0/
#30
b10011010 )
b10011010 >
b10011010 w
b1111110100111000 "
b1111110100111000 <
b1111110100111000 '"
b11101010111 %
b11101010111 =
b11101010111 ~
b1000000000 -
b1000000000 ?
b1000000000 p
1/
#35
0/
#40
b1 a
b1111110100111000 e
b11101010111 d
1/
#45
0/
#50
1/
#55
0/
#60
b1111 0
b1111 8
03
1/
#65
0/
#70
b10 g
1/
#75
0/
#80
b1 f
1/
#85
0/
#90
b1 +
b1 l
b1 u
b10 f
1/
#95
0/
#100
b10 +
b10 l
b10 u
b10011010 b
b100 f
b11001101 )
b11001101 >
b11001101 w
1/
#105
0/
#110
b100000000 )
b100000000 >
b100000000 w
b11001101 c
b1000 f
1/
#115
0/
#120
b100000000 `
b10000 f
1/
#125
0/
#130
1]
b1 f
1/
#135
0/
#140
b100 g
1/
#145
0/
#150
b1 Z
1/
#155
0/
#160
b10 Z
b0 _
b0 [
b0 h
1/
#165
0/
#170
b1000110101001010110 _
b100 Z
1/
#175
0/
#180
b11111111111111011100010111011000 _
b1000110101001010110 h
b1000 Z
1/
#185
0/
#190
b100011000000101110 h
b10000 Z
1/
#195
0/
#200
b100011000100101110 h
b100000 Z
1/
#205
0/
#210
1X
b1000000 Z
1/
#215
0/
#220
b10000000 Z
1/
#225
0/
#230
1\
b1 Z
1/
#235
0/
#240
b1000 g
1/
#245
0/
#250
b1 i
1/
#255
0/
#260
1'
b10 i
1/
#265
0/
#270
b100000000 Y
b100 i
1/
#275
0/
#280
b100000000 (
b100000000 m
b100000000 v
b11001101 k
b1000 i
1/
#285
0/
#290
b11001101 (
b11001101 m
b11001101 v
b1 +
b1 l
b1 u
b10011010 j
b10000 i
1/
#295
0/
#300
b10011010 (
b10011010 m
b10011010 v
b0 +
b0 l
b0 u
b100000 i
1/
#305
0/
#310
0'
1^
b1 i
1/
#315
0/
#320
b10000 g
b10011010 )
b10011010 >
b10011010 w
1/
#325
0/
#330
b1 g
1/
#335
0/
#340
b10 g
1/
#345
0/
#350
b100 g
1/
#355
0/
#360
b1000 g
b0 0
b0 8
1/
#365
0/
#370
1'
b10 i
0^
b1 1
b1 9
b1 n
b1 6
b1 ;
b1 %"
b1 4
b1 :
b1 |
13
1/
#375
0/
#380
0'
0\
0]
bx i
bx Z
bx f
b1 g
b0 -
b0 ?
b0 p
b1001001101 %
b1001001101 =
b1001001101 ~
b10110101110 "
b10110101110 <
b10110101110 '"
1/
#385
0/
#390
b0 a
b10110101110 e
b1001001101 d
1/
#395
0/
#400
1/
#405
0/
#410
1/
#415
0/
#420
b1111 0
b1111 8
03
1/
#425
0/
#430
b10 g
1/
#435
0/
#440
b1 f
1/
#445
0/
#450
b1 +
b1 l
b1 u
b10 f
1/
#455
0/
#460
b10 +
b10 l
b10 u
b100 f
b11001101 )
b11001101 >
b11001101 w
1/
#465
0/
#470
b100000000 )
b100000000 >
b100000000 w
b1000 f
1/
#475
0/
#480
b10000 f
1/
#485
0/
#490
1]
b1 f
1/
#495
0/
#500
b100 g
1/
#505
0/
#510
b1 Z
1/
#515
0/
#520
b10 Z
b0 _
b0 h
1/
#525
0/
#530
b10110001001010010 _
b100 Z
1/
#535
0/
#540
b1001000110001010110 _
b10110001001010010 h
b1000 Z
1/
#545
0/
#550
b1011110111010101000 h
b10000 Z
1/
#555
0/
#560
b1011110111110101000 h
b100000 Z
1/
#565
0/
#570
b1000000 Z
1/
#575
0/
#580
b1111111111111111 [
b10000000 Z
1/
#585
0/
#590
1\
b1 Z
1/
#595
0/
#600
b1000 g
1/
#605
0/
#610
b1 i
1/
#615
0/
#620
1'
b10 i
1/
#625
0/
#630
b1111111100000000 Y
b100 i
1/
#635
0/
#640
b1111111100000000 (
b1111111100000000 m
b1111111100000000 v
b1111101100011111 k
b1000 i
1/
#645
0/
#650
b1111101100011111 (
b1111101100011111 m
b1111101100011111 v
b1 +
b1 l
b1 u
b1111111001001101 j
b10000 i
1/
#655
0/
#660
b1111111001001101 (
b1111111001001101 m
b1111111001001101 v
b0 +
b0 l
b0 u
b100000 i
1/
#665
0/
#670
0'
1^
b1 i
1/
#675
0/
#680
b10000 g
b1111111001001101 )
b1111111001001101 >
b1111111001001101 w
1/
#685
0/
#690
b1 g
1/
#695
0/
#700
b10 g
1/
#705
0/
#710
b100 g
1/
#715
0/
#720
b1000 g
1/
#725
0/
#730
b10000 g
1/
#735
0/
#740
b1 g
1/
#745
0/
#750
b10 g
1/
#755
0/
#760
b100 g
1/
#765
0/
#770
b1000 g
1/
#775
0/
#780
b10000 g
1/
#785
0/
#790
b1 g
1/
#795
0/
#800
b10 g
1/
#805
0/
#810
b100 g
1/
#815
0/
#820
b1000 g
1/
#825
0/
#830
b10000 g
1/
#835
0/
#840
b1 g
1/
#845
0/
#850
b10 g
1/
#855
0/
#860
b100 g
1/
#865
0/
#870
b1000 g
1/
#875
0/
#880
b10000 g
1/
#885
0/
#890
b1 g
1/
#895
0/
#900
b10 g
1/
#905
0/
#910
b100 g
1/
#915
0/
#920
b1000 g
1/
#925
0/
#930
b10000 g
1/
#935
0/
#940
b1 g
1/
#945
0/
#950
b10 g
1/
#955
0/
#960
b100 g
1/
#965
0/
#970
b1000 g
1/
#975
0/
#980
b10000 g
1/
#985
0/
#990
b1 g
1/
#995
0/
#1000
b10 g
1/
#1005
0/
#1010
b100 g
1/
#1015
0/
#1020
b1000 g
1/
#1025
0/
#1030
b10000 g
1/
#1035
0/
#1040
b1 g
1/
#1045
0/
#1050
b10 g
1/
#1055
0/
#1060
b100 g
1/
#1065
0/
#1070
b1000 g
1/
#1075
0/
#1080
b10000 g
1/
#1085
0/
#1090
b1 g
1/
#1095
0/
#1100
b10 g
1/
#1105
0/
#1110
b100 g
1/
#1115
0/
#1120
b1000 g
1/
#1125
0/
#1130
b10000 g
1/
#1135
0/
#1140
b1 g
1/
#1145
0/
#1150
b10 g
1/
#1155
0/
#1160
b100 g
1/
#1165
0/
#1170
b1000 g
1/
#1175
0/
#1180
b10000 g
1/
#1185
0/
#1190
b1 g
1/
#1195
0/
#1200
b10 g
1/
#1205
0/
#1210
b100 g
1/
#1215
0/
#1220
b1000 g
b0 0
b0 8
1/
#1225
0/
#1230
1'
b10 i
0^
b10 1
b10 9
b10 n
b10 6
b10 ;
b10 %"
b10 4
b10 :
b10 |
13
1/
#1235
0/
#1240
0'
0\
0]
bx i
bx Z
bx f
b1 g
b1111101001111011 %
b1111101001111011 =
b1111101001111011 ~
b11011000011 "
b11011000011 <
b11011000011 '"
1/
#1245
0/
#1250
b11011000011 e
b1111101001111011 d
1/
#1255
0/
#1260
1/
#1265
0/
#1270
1/
#1275
0/
#1280
b1111 0
b1111 8
03
1/
#1285
0/
#1290
b10 g
1/
#1295
0/
#1300
b1 f
1/
#1305
0/
#1310
b1 +
b1 l
b1 u
b10 f
1/
#1315
0/
#1320
b10 +
b10 l
b10 u
b1111111001001101 b
b100 f
b1111101100011111 )
b1111101100011111 >
b1111101100011111 w
1/
#1325
0/
#1330
b1111111100000000 )
b1111111100000000 >
b1111111100000000 w
b1111101100011111 c
b1000 f
1/
#1335
0/
#1340
b1111111100000000 `
b10000 f
1/
#1345
0/
#1350
1]
b1 f
1/
#1355
0/
#1360
b100 g
1/
#1365
0/
#1370
b1 Z
1/
#1375
0/
#1380
b10 Z
b0 _
b0 [
b0 h
1/
#1385
0/
#1390
b10010110000011111111 _
b100 Z
1/
#1395
0/
#1400
b11111111110111110000001010011101 _
b10010110000011111111 h
b1000 Z
1/
#1405
0/
#1410
b11111111111010000110001110011100 h
b10000 Z
1/
#1415
0/
#1420
b11111111111010000110001010011100 h
b100000 Z
1/
#1425
0/
#1430
0X
b1000000 Z
1/
#1435
0/
#1440
b10000000 Z
1/
#1445
0/
#1450
1\
b1 Z
1/
#1455
0/
#1460
b1000 g
1/
#1465
0/
#1470
b1 i
1/
#1475
0/
#1480
1'
b10 i
1/
#1485
0/
#1490
b100 i
1/
#1495
0/
#1500
b1111111100000000 (
b1111111100000000 m
b1111111100000000 v
b1000 i
1/
#1505
0/
#1510
b1111101100011111 (
b1111101100011111 m
b1111101100011111 v
b1 +
b1 l
b1 u
b10000 i
1/
#1515
0/
#1520
b1111111001001101 (
b1111111001001101 m
b1111111001001101 v
b0 +
b0 l
b0 u
b100000 i
1/
#1525
0/
#1530
0'
1^
b1 i
1/
#1535
0/
#1540
b10000 g
b1111111001001101 )
b1111111001001101 >
b1111111001001101 w
1/
#1545
0/
#1550
b1 g
1/
#1555
0/
#1560
b10 g
1/
#1565
0/
#1570
b100 g
1/
#1575
0/
#1580
b1000 g
1/
#1585
0/
#1590
b10000 g
1/
#1595
0/
#1600
b1 g
1/
#1605
0/
#1610
b10 g
1/
#1615
0/
#1620
b100 g
1/
#1625
0/
#1630
b1000 g
1/
#1635
0/
#1640
b10000 g
1/
#1645
0/
#1650
b1 g
1/
#1655
0/
#1660
b10 g
1/
#1665
0/
#1670
b100 g
1/
#1675
0/
#1680
b1000 g
1/
#1685
0/
#1690
b10000 g
1/
#1695
0/
#1700
b1 g
1/
#1705
0/
#1710
b10 g
1/
#1715
0/
#1720
b100 g
1/
#1725
0/
#1730
b1000 g
1/
#1735
0/
#1740
b10000 g
1/
#1745
0/
#1750
b1 g
1/
#1755
0/
#1760
b10 g
1/
#1765
0/
#1770
b100 g
1/
#1775
0/
#1780
b1000 g
1/
#1785
0/
#1790
b10000 g
1/
#1795
0/
#1800
b1 g
1/
#1805
0/
#1810
b10 g
1/
#1815
0/
#1820
b100 g
1/
#1825
0/
#1830
b1000 g
1/
#1835
0/
#1840
b10000 g
1/
#1845
0/
#1850
b1 g
1/
#1855
0/
#1860
b10 g
1/
#1865
0/
#1870
b100 g
1/
#1875
0/
#1880
b1000 g
1/
#1885
0/
#1890
b10000 g
1/
#1895
0/
#1900
b1 g
1/
#1905
0/
#1910
b10 g
1/
#1915
0/
#1920
b100 g
1/
#1925
0/
#1930
b1000 g
1/
#1935
0/
#1940
b10000 g
1/
#1945
0/
#1950
b1 g
1/
#1955
0/
#1960
b10 g
1/
#1965
0/
#1970
b100 g
1/
#1975
0/
#1980
b1000 g
1/
#1985
0/
#1990
b10000 g
1/
#1995
0/
#2000
b1 g
1/
#2005
0/
#2010
b10 g
1/
#2015
0/
#2020
b100 g
1/
#2025
0/
#2030
b1000 g
1/
#2035
0/
#2040
b10000 g
1/
#2045
0/
#2050
b1 g
1/
#2055
0/
#2060
b10 g
1/
#2065
0/
#2070
b100 g
1/
#2075
0/
#2080
b1000 g
b0 0
b0 8
1/
#2085
0/
#2090
1'
b10 i
0^
b11 1
b11 9
b11 n
b11 6
b11 ;
b11 %"
b11 4
b11 :
b11 |
13
1/
#2095
0/
#2100
0'
0\
0]
bx i
bx Z
bx f
b1 g
b1111011111100001 %
b1111011111100001 =
b1111011111100001 ~
b11001010111 "
b11001010111 <
b11001010111 '"
1/
#2105
0/
#2110
b11001010111 e
b1111011111100001 d
1/
#2115
0/
#2120
1/
#2125
0/
#2130
1/
#2135
0/
#2140
b1111 0
b1111 8
03
1/
#2145
0/
#2150
b10 g
1/
#2155
0/
#2160
b1 f
1/
#2165
0/
#2170
b1 +
b1 l
b1 u
b10 f
1/
#2175
0/
#2180
b10 +
b10 l
b10 u
b100 f
b1111101100011111 )
b1111101100011111 >
b1111101100011111 w
1/
#2185
0/
#2190
b1111111100000000 )
b1111111100000000 >
b1111111100000000 w
b1000 f
1/
#2195
0/
#2200
b10000 f
1/
#2205
0/
#2210
1]
b1 f
1/
#2215
0/
#2220
b100 g
1/
#2225
0/
#2230
b1 Z
1/
#2235
0/
#2240
b10 Z
b0 _
b0 h
1/
#2245
0/
#2250
b11011100110010101101 _
b100 Z
1/
#2255
0/
#2260
b11111111111000010001000110001001 _
b11011100110010101101 h
b1000 Z
1/
#2265
0/
#2270
b11111111111011101101111000110110 h
b10000 Z
1/
#2275
0/
#2280
b11111111111011101101110100110110 h
b100000 Z
1/
#2285
0/
#2290
b1000000 Z
1/
#2295
0/
#2300
b10000000 Z
1/
#2305
0/
#2310
1\
b1 Z
1/
#2315
0/
#2320
b1000 g
1/
#2325
0/
#2330
b1 i
1/
#2335
0/
#2340
1'
b10 i
1/
#2345
0/
#2350
b100 i
1/
#2355
0/
#2360
b1111111100000000 (
b1111111100000000 m
b1111111100000000 v
b1000 i
1/
#2365
0/
#2370
b1111101100011111 (
b1111101100011111 m
b1111101100011111 v
b1 +
b1 l
b1 u
b10000 i
1/
#2375
0/
#2380
b1111111001001101 (
b1111111001001101 m
b1111111001001101 v
b0 +
b0 l
b0 u
b100000 i
1/
#2385
0/
#2390
0'
1^
b1 i
1/
#2395
0/
#2400
b10000 g
b1111111001001101 )
b1111111001001101 >
b1111111001001101 w
1/
#2405
0/
#2410
b1 g
1/
#2415
0/
#2420
b10 g
1/
#2425
0/
#2430
b100 g
1/
#2435
0/
#2440
b1000 g
1/
#2445
0/
#2450
b10000 g
1/
#2455
0/
#2460
b1 g
1/
#2465
0/
#2470
b10 g
1/
#2475
0/
#2480
b100 g
1/
#2485
0/
#2490
b1000 g
1/
#2495
0/
#2500
b10000 g
1/
#2505
0/
#2510
b1 g
1/
#2515
0/
#2520
b10 g
1/
#2525
0/
#2530
b100 g
1/
#2535
0/
#2540
b1000 g
1/
#2545
0/
#2550
b10000 g
1/
#2555
0/
#2560
b1 g
1/
#2565
0/
#2570
b10 g
1/
#2575
0/
#2580
b100 g
1/
#2585
0/
#2590
b1000 g
1/
#2595
0/
#2600
b10000 g
1/
#2605
0/
